aiserve/__init__.py
aiserve/_internal/__init__.py
aiserve/main.py
aiserve-0.0.2.dist-info/METADATA
aiserve-0.0.2.dist-info/WHEEL
aiserve-0.0.2.dist-info/RECORD
